instantnews.py
setup.cfg
setup.py
instantnews.egg-info/PKG-INFO
instantnews.egg-info/SOURCES.txt
instantnews.egg-info/dependency_links.txt
instantnews.egg-info/entry_points.txt
instantnews.egg-info/requires.txt
instantnews.egg-info/top_level.txt