Metadata-Version: 1.0
Name: instantnews
Version: 1.2.4
Summary: Get live news instantaneously
Home-page: https://github.com/shivam043/instantnews
Author: shivam singh
Author-email: shivam043@gmail.com
License: MIT
Platform: UNKNOWN
